LICENSE
MANIFEST.in
README.rst
setup.py
flinck/__init__.py
flinck/__version__.py
flinck/brain.py
flinck/config.py
flinck/confit.py
flinck/linker.py
flinck.egg-info/PKG-INFO
flinck.egg-info/SOURCES.txt
flinck.egg-info/dependency_links.txt
flinck.egg-info/entry_points.txt
flinck.egg-info/pbr.json
flinck.egg-info/requires.txt
flinck.egg-info/top_level.txt