Metadata-Version: 1.1
Name: flinck
Version: 0.3.2
Summary: Sort your movies on filesystem using symlinks.
Home-page: https://github.com/KraYmer/flinck
Author: Fabrice Laporte
Author-email: kraymer@gmail.com
License: MIT
Platform: ALL
Classifier: License :: OSI Approved :: MIT License
Classifier: Programming Language :: Python
Classifier: Environment :: Console
Classifier: Topic :: System :: Filesystems
Classifier: Topic :: Multimedia :: Video
